sheetwise/__init__.py
sheetwise/__main__.py
sheetwise/chain.py
sheetwise/classifiers.py
sheetwise/cli.py
sheetwise/compressor.py
sheetwise/core.py
sheetwise/data_types.py
sheetwise/detectors.py
sheetwise/encoders.py
sheetwise/extractors.py
sheetwise/formula_parser.py
sheetwise/loaders.py
sheetwise/privacy.py
sheetwise/smart_tables.py
sheetwise/utils.py
sheetwise/visualizer.py
sheetwise/workbook.py
sheetwise-2.8.0.dist-info/METADATA
sheetwise-2.8.0.dist-info/WHEEL
sheetwise-2.8.0.dist-info/entry_points.txt
sheetwise-2.8.0.dist-info/licenses/LICENSE
sheetwise-2.8.0.dist-info/RECORD
