Metadata-Version: 2.4
Name: sheetwise
Version: 2.8.0
Summary: A Python package for encoding spreadsheets for Large Language Models, implementing the SpreadsheetLLM research framework
Author-email: Khushiyant Chauhan <khushiyant2002@gmail.com>
License: MIT
License-File: LICENSE
Keywords: compression,data-processing,encoding,llm,spreadsheet
Classifier: Development Status :: 4 - Beta
Classifier: Intended Audience :: Developers
Classifier: Intended Audience :: Science/Research
Classifier: License :: OSI Approved :: MIT License
Classifier: Operating System :: OS Independent
Classifier: Programming Language :: Python :: 3
Classifier: Topic :: Scientific/Engineering :: Information Analysis
Classifier: Topic :: Software Development :: Libraries :: Python Modules
Classifier: Topic :: Text Processing :: General
Requires-Python: >=3.10
Requires-Dist: duckdb>=1.4.3
Requires-Dist: matplotlib>=3.6.0
Requires-Dist: numpy>=1.21.0
Requires-Dist: openpyxl>=3.1.0
Requires-Dist: pandas>=2.0.0
Requires-Dist: pillow>=10.0.0
Requires-Dist: requests>=2.28.0
Requires-Dist: rich>=14.1.0
Requires-Dist: seaborn>=0.13.2
Requires-Dist: thefuzz>=0.22.1
Requires-Dist: xlrd>=2.0.2
